an_easyven/__init__.py
an_easyven/easyven.py
an_easyven-0.8.0.dist-info/licenses/LICENSE
an_easyven-0.8.0.dist-info/METADATA
an_easyven-0.8.0.dist-info/WHEEL
an_easyven-0.8.0.dist-info/top_level.txt
an_easyven-0.8.0.dist-info/RECORD
