Metadata-Version: 2.4
Name: an_easyven
Version: 0.8.0
Summary: A package for an_easyven.
Home-page: https://github.com/Atsushi888/Atsushi888
Author: Atsushi888
Author-email: Atsushi888 <vtgrotxu@gmail.com>
Project-URL: Homepage, https://github.com/Atsushi888/an_easyven
Project-URL: Repository, https://github.com/Atsushi888/an_easyven
Requires-Python: >=3.6
License-File: LICENSE
Requires-Dist: an_EnvManager
Dynamic: author
Dynamic: home-page
Dynamic: license-file
Dynamic: requires-python
